Full_Adder/full_adder.v
module half_adder(s,c,a,b);
input a,b;
output s,c;
assign s=a^b;
assign c=a&b;
endmodule

module full_adder(sum,cout,a,b,cin);
input a,b,cin;
output sum,cout;
wire w1,w2,w3;

half_adder ha0(w1,w2,a,b);
half_adder ha1(sum,w3,w1,cin);
or or0(cout,w3,w2);
endmodule

Full_Adder/full_adder_tb.v
`include "full_adder.v"

module full_adder_tb;
reg a,b,cin;
wire sum,cout;

full_adder dut(sum,cout,a,b,cin);

initial begin
  $dumpfile("full_adder.vcd");
  $dumpvars(0,full_adder_tb);

  a=0;b=0;cin=0;
  #10;
  a=0;b=0;cin=1;
  #10;
  a=0;b=1;cin=0;
  #10;
  a=0;b=1;cin=1;
  #10;
  a=1;b=0;cin=0;
  #10;
  a=1;b=0;cin=1;
  #10;
  a=1;b=1;cin=0;
  #10;
  a=1;b=1;cin=1;
  #10;

  $display("Testing Done");

end
endmodule

Full_Adder/full_adder.vcd
$date
	Mon Sep 19 17:52:29 2022
$end
$version
	Icarus Verilog
$end
$timescale
	1s
$end
$scope module full_adder_tb $end
$var wire 1 ! cout $end
$var wire 1 " sum $end
$var reg 1 # a $end
$var reg 1 $ b $end
$var reg 1 % cin $end
$scope module dut $end
$var wire 1 & a $end
$var wire 1 ' b $end
$var wire 1 ( cin $end
$var wire 1 ! cout $end
$var wire 1 " sum $end
$var wire 1 ) w1 $end
$var wire 1 * w2 $end
$var wire 1 + w3 $end
$scope module ha0 $end
$var wire 1 & a $end
$var wire 1 ' b $end
$var wire 1 * c $end
$var wire 1 ) s $end
$upscope $end
$scope module ha1 $end
$var wire 1 ) a $end
$var wire 1 ( b $end
$var wire 1 + c $end
$var wire 1 " s $end
$upscope $end
$upscope $end
$upscope $end
$enddefinitions $end
#0
$dumpvars
0+
0*
0)
0(
0'
0&
0%
0$
0#
0"
0!
$end
#10
1"
1%
1(
#20
1)
0%
0(
1$
1'
#30
1!
0"
1+
1%
1(
#40
0!
1"
0+
0%
0(
0$
0'
1#
1&
#50
1!
0"
1+
1%
1(
#60
0+
0)
1*
0%
0(
1$
1'
#70
1"
1%
1(
